<?xml version="1.0" encoding="utf-8"?>
<item label="/" id="0" title="［3-1-10］ 早船木割" description="" dpi="150" total="19">
<item label="表紙 (1/19)" id="1" page="1" resource="3-1-10/3-1-10_001" ext="jpg" ldata="128,97" />
<item label="(2/19)" id="2" page="2" resource="3-1-10/3-1-10_002" ext="jpg" ldata="128,97" />
<item label="(3/19)" id="3" page="3" resource="3-1-10/3-1-10_003" ext="jpg" ldata="128,97" />
<item label="(4/19)" id="4" page="4" resource="3-1-10/3-1-10_004" ext="jpg" ldata="128,97" />
<item label="(5/19)" id="5" page="5" resource="3-1-10/3-1-10_005" ext="jpg" ldata="128,97" />
<item label="(6/19)" id="6" page="6" resource="3-1-10/3-1-10_006" ext="jpg" ldata="128,97" />
<item label="(7/19)" id="7" page="7" resource="3-1-10/3-1-10_007" ext="jpg" ldata="128,97" />
<item label="(8/19)" id="8" page="8" resource="3-1-10/3-1-10_008" ext="jpg" ldata="128,97" />
<item label="(9/19)" id="9" page="9" resource="3-1-10/3-1-10_009" ext="jpg" ldata="128,97" />
<item label="(10/19)" id="10" page="10" resource="3-1-10/3-1-10_010" ext="jpg" ldata="128,97" />
<item label="(11/19)" id="11" page="11" resource="3-1-10/3-1-10_011" ext="jpg" ldata="128,97" />
<item label="(12/19)" id="12" page="12" resource="3-1-10/3-1-10_012" ext="jpg" ldata="128,97" />
<item label="(13/19)" id="13" page="13" resource="3-1-10/3-1-10_013" ext="jpg" ldata="128,97" />
<item label="(14/19)" id="14" page="14" resource="3-1-10/3-1-10_014" ext="jpg" ldata="128,97" />
<item label="(15/19)" id="15" page="15" resource="3-1-10/3-1-10_015" ext="jpg" ldata="128,97" />
<item label="(16/19)" id="16" page="16" resource="3-1-10/3-1-10_016" ext="jpg" ldata="128,97" />
<item label="(17/19)" id="17" page="17" resource="3-1-10/3-1-10_017" ext="jpg" ldata="128,97" />
<item label="(18/19)" id="18" page="18" resource="3-1-10/3-1-10_018" ext="jpg" ldata="128,97" />
<item label="(19/19)" id="19" page="19" resource="3-1-10/3-1-10_019" ext="jpg" ldata="128,97" />
</item>
